{
  "_id": "Authenticated",
  "permissions": {
    "collection: view relevant": true,
    "schemas: view": true,
    "view errors": false,
    "collection: create": false,
    "collection: delete": false,
    "collection: edit": false,
    "collection: view": false,
    "email_signups: create": true,
    "email_signups: delete": false,
    "email_signups: edit": false,
    "email_signups: view": false,
    "leads: create": false,
    "leads: delete": false,
    "leads: edit": false,
    "leads: view": false,
    "race: create": false,
    "race: delete": false,
    "race: edit": false,
    "race: view": false,
    "role: create": false,
    "role: delete": false,
    "role: edit": false,
    "role: view": false,
    "settings: create": false,
    "settings: delete": false,
    "settings: edit": false,
    "settings: view": false,
    "users: create": false,
    "users: delete": false,
    "users: delete own": false,
    "users: edit": false,
    "users: edit own": false,
    "users: modify roles": false,
    "users: view": false,
    "users: view hashed passwords": false,
    "users: view own": true,
    "contacts: create": false,
    "contacts: delete": false,
    "contacts: edit": false,
    "contacts: view": false,
    "partner_payments: create": false,
    "partner_payments: delete": false,
    "partner_payments: edit": false,
    "partner_payments: view": false,
    "user_payments: create": false,
    "user_payments: delete": false,
    "user_payments: edit": false,
    "user_payments: view": false,
    "promo_code: create": false,
    "promo_code: delete": false,
    "promo_code: edit": false,
    "promo_code: view": true,
    "race_signup: create": true,
    "race_signup: delete": false,
    "race_signup: delete own": false,
    "race_signup: edit": false,
    "race_signup: edit own": true,
    "race_signup: view": false,
    "race_signup: view own": true
  },
  "meta": {
    "created": "2016-12-14T08:09:54.886Z",
    "updated": "2017-03-14T07:30:55.916Z"
  }
}